indico_storage_s3/__init__.py
indico_storage_s3/blueprint.py
indico_storage_s3/controllers.py
indico_storage_s3/import_event_files.py
indico_storage_s3/migrate.py
indico_storage_s3/plugin.py
indico_storage_s3/storage.py
indico_storage_s3/task.py
indico_storage_s3/util.py
indico_storage_s3/translations/messages.pot
indico_storage_s3/translations/cs_CZ/LC_MESSAGES/messages.mo
indico_storage_s3/translations/cs_CZ/LC_MESSAGES/messages.po
indico_storage_s3/translations/de_DE/LC_MESSAGES/messages.mo
indico_storage_s3/translations/de_DE/LC_MESSAGES/messages.po
indico_storage_s3/translations/en_CA/LC_MESSAGES/messages.mo
indico_storage_s3/translations/en_CA/LC_MESSAGES/messages.po
indico_storage_s3/translations/en_GB/LC_MESSAGES/messages.mo
indico_storage_s3/translations/en_GB/LC_MESSAGES/messages.po
indico_storage_s3/translations/es_ES/LC_MESSAGES/messages.mo
indico_storage_s3/translations/es_ES/LC_MESSAGES/messages.po
indico_storage_s3/translations/fr_FR/LC_MESSAGES/messages.mo
indico_storage_s3/translations/fr_FR/LC_MESSAGES/messages.po
indico_storage_s3/translations/hu_HU/LC_MESSAGES/messages.mo
indico_storage_s3/translations/hu_HU/LC_MESSAGES/messages.po
indico_storage_s3/translations/it_IT/LC_MESSAGES/messages.mo
indico_storage_s3/translations/it_IT/LC_MESSAGES/messages.po
indico_storage_s3/translations/ja_JP/LC_MESSAGES/messages.mo
indico_storage_s3/translations/ja_JP/LC_MESSAGES/messages.po
indico_storage_s3/translations/mn_MN/LC_MESSAGES/messages.mo
indico_storage_s3/translations/mn_MN/LC_MESSAGES/messages.po
indico_storage_s3/translations/pl_PL/LC_MESSAGES/messages.mo
indico_storage_s3/translations/pl_PL/LC_MESSAGES/messages.po
indico_storage_s3/translations/pt_BR/LC_MESSAGES/messages.mo
indico_storage_s3/translations/pt_BR/LC_MESSAGES/messages.po
indico_storage_s3/translations/sv_SE/LC_MESSAGES/messages.mo
indico_storage_s3/translations/sv_SE/LC_MESSAGES/messages.po
indico_storage_s3/translations/tr_TR/LC_MESSAGES/messages.mo
indico_plugin_storage_s3-3.3.2.dist-info/METADATA
indico_plugin_storage_s3-3.3.2.dist-info/WHEEL
indico_plugin_storage_s3-3.3.2.dist-info/entry_points.txt
indico_plugin_storage_s3-3.3.2.dist-info/RECORD
